pycipher/HillCipher.py
pycipher/__init__.py
pycipher/__main__.py
pyciphers/HillCipher.py
pyciphers/__init__.py
pyciphers/__main__.py
pyciphers-1.0.0.dist-info/METADATA
pyciphers-1.0.0.dist-info/WHEEL
pyciphers-1.0.0.dist-info/entry_points.txt
pyciphers-1.0.0.dist-info/top_level.txt
pyciphers-1.0.0.dist-info/RECORD
