Metadata-Version: 2.1
Name: pyciphers
Version: 1.0.0
Summary: The Hill cipher Encryption algorithm is one of the symmetric key algorithms that have several advantages in data encryption.
Home-page: https://github.com/Yashmodi59/Cipher_Python_Package
Author: Yash Modi
Author-email: yashmodi2059@gmail.com
License: MIT
Platform: UNKNOWN
Classifier: License :: OSI Approved :: MIT License
Classifier: Programming Language :: Python :: 3
Classifier: Programming Language :: Python :: 3.7
Requires-Dist: numpy
